 [{"countryCode":"AD","cities":["Andorra la Vella"]},{"countryCode":"AE","cities":["Abu Dhabi","Ajman","Dubai","Sharjah","United Arab Emirates"]},{"countryCode":"AF","cities":[]},{"countryCode":"AL","cities":["KOSOVE","Kosovë","Tirana"]},{"countryCode":"AM","cities":["Yerevan"]},{"countryCode":"AO","cities":["Luanda"]},{"countryCode":"AR","cities":["Argentina","Autonomous City of Buenos Aires","Buenos Aires","Buenos Aires Province","Comodoro Rivadavia","Córdoba","Mendoza","Misiones Province","Morón","Olivos","Rafaela","Ramos Mejía","Rosario","San Miguel de Tucumán","Trelew","Tres Arroyos","Venado Tuerto"]},{"countryCode":"AT","cities":["Judenburg","Kitzbuhel","Salzburg","Vienna","Wien"]},{"countryCode":"AU","cities":["Adelaide","Australia","Bald Hills","Brisbane","Brisbane City","Canberra","Chatswood","Melbourne","New Farm","Penrith","Perth","Shepparton","Sydney","Victoria"]},{"countryCode":"AW","cities":[]},{"countryCode":"AZ","cities":["Baku"]},{"countryCode":"BA","cities":["Banja Luka","Mostar","Sarajevo"]},{"countryCode":"BD","cities":["Dhaka"]},{"countryCode":"BE","cities":["Arlon","Brussels","Bruxelles","Ghent","Hasselt","Uccle"]},{"countryCode":"BG","cities":["Plovdiv","Sofia"]},{"countryCode":"BH","cities":[]},{"countryCode":"BI","cities":[]},{"countryCode":"BJ","cities":["Cotonou"]},{"countryCode":"BM","cities":[]},{"countryCode":"BN","cities":[]},{"countryCode":"BO","cities":["Bolivia","La Paz","La Paz Department","Santa Cruz de la Sierra"]},{"countryCode":"BR","cities":["Belém","Belo Horizonte","Boa Vista","Botucatu","Brasília","Brasília de Minas","Brazil","Campinas","Curitiba","Distrito Federal","Florianópolis","Goiânia","Manaus","Maringá","Porto Alegre","Rio de Janeiro","Santa Cruz do Sul","São José","São Paulo","State of Ceará","State of Espírito Santo","State of Minas Gerais","State of Rio de Janeiro","State of Santa Catarina","State of São Paulo","State of Tocantins","Vila Velha"]},{"countryCode":"BS","cities":[]},{"countryCode":"BT","cities":["Thimphu"]},{"countryCode":"BW","cities":["Francistown"]},{"countryCode":"BY","cities":["Brest","Gomel","Minsk","Mogilev","Mogilev Region"]},{"countryCode":"CA","cities":["Abbotsford","Alberta","Barrie","Brampton","British Columbia","Calgary","Canada","Coquitlam","Delta","Edmonton","Guelph","Halifax","Hamilton","Kamloops","Kelowna","Kingston","Kitchener","Labrador City","Lethbridge","London","Markham","Midland","Milton","Mississauga","Moncton","Montreal","Montréal","Nanaimo","Niagara Falls","Oakville","Ontario","Ottawa","Pemberton","Penticton","Peterborough","Québec City","Richmond Hill","Sarnia","Saskatoon","Sherbrooke","Terrace","Toronto","Trois-Rivières","Vancouver","Vernon","Victoria","Whistler","Winnipeg"]},{"countryCode":"CD","cities":["Lubumbashi"]},{"countryCode":"CF","cities":[]},{"countryCode":"CG","cities":[]},{"countryCode":"CH","cities":["Aargau","Basel","Basel City","Basel-Stadt","Bern","Geneva","Kreuzlingen","Kriens","Lucerne","Lugano","Montreux","Werdenberg","Zurich","Zürich"]},{"countryCode":"CI","cities":["Abidjan"]},{"countryCode":"CL","cities":["Chile","Chile, Chile","Las Condes","Los Ángeles","Santiago","Santiago Metropolitan Region","Temuco","Valparaíso","Viña del Mar"]},{"countryCode":"CM","cities":["Buea","Cameroon","Douala"]},{"countryCode":"CN","cities":["Beijing","Changsha","Chengdu","China","China, China","Dezhou","Fuzhou","Guangdong","Guangxi","Guangzhou","Hangzhou","Hefei","Hubei","Huizhou","Hunan","Jinan","Jinhua","Jining","Nanchang","Shanghai","Shenyang","Shenzhen","Suzhou","Tianjin","Wuhan","Xiamen","Xuchang","Yantai","Zaozhuang","Zhejiang"]},{"countryCode":"CO","cities":["Antioquia","Arauca","Armenia","Barranquilla","Bogota","Bogotá","Bucaramanga","Buga","Cali","Cartagena","Colombia","Cúcuta","Duitama","Envigado","Girón","Huila","Ibagué","Itagüí","Manizales","Medellín","Neiva","North Santander","Pasto","Pereira","Popayán","Putumayo","Quindio","Riosucio","Santa Marta","Santander","Santander Department","Tolima","Tulua","Valle del Cauca","Villavicencio","Zipaquirá"]},{"countryCode":"CR","cities":["Costa Rica","Heredia","Heredia Province","San Jose","San José","San José Province","Upala"]},{"countryCode":"CU","cities":[]},{"countryCode":"CW","cities":[]},{"countryCode":"CY","cities":[]},{"countryCode":"CZ","cities":["Brno","Dolní Bečva","Prague","Třebíč"]},{"countryCode":"DK","cities":["Copenhagen","Kerteminde"]},{"countryCode":"DO","cities":["La Romana","Santo Domingo","Sosúa"]},{"countryCode":"EC","cities":["Atuntaqui","Ecuador","Guayaquil","Machala","Quito"]},{"countryCode":"EE","cities":["Harju maakond","Tallinn","Tartu"]},{"countryCode":"EG","cities":["Alexandria","Cairo Governorate","Egypt","Giza Governorate","New Cairo City","Shubra Al Kheimah","Sohag"]},{"countryCode":"ES","cities":["A Coruña","Andalusia","Barcelona","Bilbao","Canary Islands","Catalonia","Girona","Huelva","León","Lleida","Madrid","Maioris Decima","Málaga","Murcia","Palma","Reus","Sa Pobla","Spain","Tarragona","Valencia","València","Valencian Community","Vigo","Zaragoza"]},{"countryCode":"FI","cities":["Helsinki","Oulu"]},{"countryCode":"FO","cities":["Tórshavn"]},{"countryCode":"FR","cities":["Aix-les-Bains","Annemasse","Antibes","Arcachon","Biarritz","Bordeaux","Cannes","Châlons-en-Champagne","Colmar","France","Goussainville","Grenoble","Île-de-France","La Crau","La Réunion","Le Bourget","Lille","Lyon","Lyon-3E-Arrondissement","Marseille","Matha","Mimizan","Mulhouse","Nice","Paris","Saint-Denis","Saint-Louis","Saintes","Suresnes","Toulouse","Vincennes"]},{"countryCode":"GA","cities":[]},{"countryCode":"GB","cities":["Bedford","Belfast","Birmingham","Bournemouth","Brighton","Bristol","Cambridge","Cardiff","Chichester","Clacton-on-Sea","Coventry","Croydon","Edinburgh","England","Exeter","Glasgow","Greenford","Haywards Heath","Ilford","Leicester","Lightwater","Lincoln","Liverpool","London","London Borough of Ealing","London Borough of Hackney","London Borough of Hillingdon","Longford","Luton","Manchester","Nottingham","Oxford","Peterborough","Poole","Portsmouth","Preston","Reading","Richmond","Ringwood","Sheffield","Sidcup","Southall","Southampton","Stevenage","Stroud","Surbiton","Sutton","Swansea","Tewkesbury","Toddington","Twickenham","United Kingdom","Uxbridge","Wales","Warrington","Wembley","Windsor","Wolverhampton","Yeovil","York"]},{"countryCode":"GE","cities":["Batumi","Tbilisi"]},{"countryCode":"GH","cities":["Accra","Amasaman","Kumasi"]},{"countryCode":"GI","cities":["Gibraltar"]},{"countryCode":"GL","cities":[]},{"countryCode":"GM","cities":[]},{"countryCode":"GR","cities":["Alexandroupoli","Athens","Greece","Kallithea","Peristeri","Piraeus","Pireas","Thessaloniki"]},{"countryCode":"GT","cities":["Guatemala City"]},{"countryCode":"HK","cities":["Hong Kong","Hong Kong Island"]},{"countryCode":"HM","cities":[]},{"countryCode":"HN","cities":["San Pedro Sula","Tegucigalpa"]},{"countryCode":"HR","cities":["Zagreb"]},{"countryCode":"HT","cities":[]},{"countryCode":"HU","cities":["Budapest","Dunaújváros","Hungary","Zalaegerszeg"]},{"countryCode":"ID","cities":["Jakarta","Semarang"]},{"countryCode":"IE","cities":["Cork","County Cork","Dublin"]},{"countryCode":"IL","cities":["Afula","Jerusalem","Karmiel"]},{"countryCode":"IN","cities":["Agra","Ahmedabad","Aurangabad","Bareilly","Bengaluru","Bhubaneswar","Bulandshahr","Chandigarh","Chennai","Dehradun","Delhi","Erode","Greater Noida","Gujarat","Gurugram","Hyderabad","India","India, India","Jabalpur","Jaipur","Karnataka","Kerala","Kolkata","Kota","Lucknow","Madhya Pradesh","Mumbai","New Delhi","Noida","Patna","Pune","Punjab","Puri","Rajasthan","Rudrapur","Surat","Thane","Tiruchirappalli","Uttar Pradesh","Vapi","Vellore","Visakhapatnam"]},{"countryCode":"IQ","cities":[]},{"countryCode":"IR","cities":["Fars Province","Golestan","Isfahan","Isfahan Province","Qeshm","Shiraz","Tehran","Tehran Province"]},{"countryCode":"IS","cities":["Reykjavík"]},{"countryCode":"IT","cities":["Avellino","Aversa","Benevento","Bologna","Brescia","Caltagirone","Catania","Cosenza","Crema","Dolo","Eboli","Emilia-Romagna","Friuli-Venezia Giulia","Gorizia","Italy","Lazio","Livorno","Locorotondo","Lombardy","Lugo","Mantua","Milan","Modena","Naples","Napoli","Padova","Padua","Pavia","Piedmont","Pozzuoli","Riva del Garda","Rome","Salerno","Santena","Sicily","Treviso","Turin","Tuscany","Udine","Varese","Veneto","Venice","Verona","Vicenza"]},{"countryCode":"JE","cities":[]},{"countryCode":"JM","cities":[]},{"countryCode":"JO","cities":["Amman"]},{"countryCode":"JP","cities":["Japan, Japan","Tokyo"]},{"countryCode":"KE","cities":["Athi River","Kenya","Mombasa","Nairobi","Nairobi County","Nakuru","Nakuru County","Narok","Ruaka","Thika"]},{"countryCode":"KG","cities":["Bishkek","Karakol"]},{"countryCode":"KH","cities":["Phnom Penh"]},{"countryCode":"KR","cities":["Busan","Daejeon","Gumi-si","Gyeonggi-do","Seoul"]},{"countryCode":"KW","cities":["Kuwait","Kuwait City","Salmiya"]},{"countryCode":"KY","cities":[]},{"countryCode":"KZ","cities":["Almaty","Almaty Province","Astana","East Kazakhstan Province","Karagandy","Kazachstan","Kazakhstan","Shymkent"]},{"countryCode":"LB","cities":["Beirut"]},{"countryCode":"LI","cities":["Vaduz"]},{"countryCode":"LK","cities":["Colombo"]},{"countryCode":"LS","cities":[]},{"countryCode":"LT","cities":["Vilnius"]},{"countryCode":"LU","cities":["Luxembourg City"]},{"countryCode":"LV","cities":["Latvia","Riga"]},{"countryCode":"MA","cities":["Casablanca","Fes","Marrakesh","Morocco","Rabat","Tangier","Tetouan"]},{"countryCode":"MC","cities":["Monaco-Ville"]},{"countryCode":"MD","cities":["Chisinau","Chișinău"]},{"countryCode":"ME","cities":["Podgorica","Tivat"]},{"countryCode":"MG","cities":[]},{"countryCode":"MK","cities":["Macedonia (FYROM)","Prilep","Skopje"]},{"countryCode":"ML","cities":["Bamako"]},{"countryCode":"MM","cities":["Mandalay","Yangon","Yangon Region"]},{"countryCode":"MN","cities":[]},{"countryCode":"MO","cities":["Macau"]},{"countryCode":"MT","cities":[]},{"countryCode":"MU","cities":["Mauritius","Port Louis"]},{"countryCode":"MV","cities":[]},{"countryCode":"MW","cities":[]},{"countryCode":"MX","cities":["Guadalajara","Heroica Puebla de Zaragoza","Jalisco","Leon","Mexico","México","Mexico City","Michoacán","Nayarit","Puebla City","Querétaro","Tejupilco de Hidalgo","Tijuana","Tuxtla Gutiérrez"]},{"countryCode":"MY","cities":["Federal Territory of Kuala Lumpur","George Town","Johor","Johor Bahru","Kota Kinabalu","Kuala Lumpur","Kuching","Lumut","Malaysia","Miri","Penang","Petaling Jaya","Seberang Jaya","Selangor","Shah Alam","Subang Jaya"]},{"countryCode":"MZ","cities":[]},{"countryCode":"NA","cities":[]},{"countryCode":"NE","cities":[]},{"countryCode":"NF","cities":[]},{"countryCode":"NG","cities":["Aba","Abuja","Akure","Akwa Ibom","Anambra","Asaba","Awka","Bayelsa","Benin City","Delta","Edo","Enugu","FCT","Ibadan","Ikeja","Ilorin","Jos","Kaduna","Kano","Keffi","Lagos","Lekki","Logbara","Niger","Nigeria","Ogun State","Ondo","Osun","Owerri","Oyo","Port Harcourt","Rivers","Sapele","Umuahia","Ungwan Patachi","Uyo","Warri"]},{"countryCode":"NI","cities":["Managua"]},{"countryCode":"NL","cities":["Amsterdam","Maastricht","Nederweert","Netherlands"]},{"countryCode":"NO","cities":["Bergen","Florø","Lillestrøm","Lørenskog","Norway","Oslo","Sandnes","Trondheim"]},{"countryCode":"NP","cities":[]},{"countryCode":"NZ","cities":["Auckland","Christchurch","Dunedin","Hamilton","Northland","Palmerston North","Taupo","Waikato","Wellington","Whangarei"]},{"countryCode":"OM","cities":["Muscat","Muscat Governorate","Oman","Salalah"]},{"countryCode":"PA","cities":["Panama","Panama City"]},{"countryCode":"PE","cities":["Arequipa","Ate","Bellavista District","Cercado de Lima","Chiclayo","Chimbote","Distrito de San Isidro","Huancayo","Independencia","Iquitos","Junin","La Molina","Lima","Lima District","Lima Region","Lurin","Moyobamba","Peru","Piura","Santiago de Surco","Tacna","Trujillo"]},{"countryCode":"PH","cities":["Caloocan","Cebu City","Dasmariñas","Manila","Parañaque","Pasay","Quezon City","Taguig"]},{"countryCode":"PK","cities":["Bahawalpur","Burewala","Faisalabad","Federal Capital Territory","Gujar Khan","Gujranwala","Islamabad","Islamabad Capital Territory","Jalalpur Pirwala","Karachi","Lahore","Larkana","Mardan","Mianwali","Multan","Pakistan","Peshawar","Rahim Yar Khan","Rawalpindi","Shahdādkot","Sialkot","Sindh","Wazirabad"]},{"countryCode":"PL","cities":["Bydgoszcz","Gdynia","Gliwice","Kraków","Leonardów","Lublin","Rzeszow","Warsaw","Warszawa","Wrocław"]},{"countryCode":"PR","cities":[]},{"countryCode":"PS","cities":[]},{"countryCode":"PT","cities":["Aveiro District","Braga","Faro District","Leiria","Lisbon","Porto","Portugal","Santa Maria da Feira","Santarem","Trafaria","Vila Nova de Gaia"]},{"countryCode":"PY","cities":["Asuncion"]},{"countryCode":"QA","cities":["Doha"]},{"countryCode":"RO","cities":["Alexandria","Bacău","Bacău County","Brașov","Brașov County","Bucharest","București","Cluj County","Cluj-Napoca","Constanța","Constanța County","Craiova","Dolj County","Drobeta-Turnu Severin","Focșani","Galați","Gura Humorului","Iași","Ilfov County","Oradea","Piatra Neamț","Pitești","Ploiești","Râmnicu Vâlcea","Romania","Sibiu","Sinaia","Suceava","Târgu Jiu","Turda","Vâlcea County","Vâlcea County, Romania, Romania","Vaslui County"]},{"countryCode":"RS","cities":["Belgrade","Novi Sad"]},{"countryCode":"RU","cities":["Adler","Altai Krai","Arkhangelsk Oblast","Armavir","Balashikha","Barnaul","Bolshoy Sochi","Bryansk Oblast","Chechnya","Chelyabinsk","Cherkessk","Chuvashia Republic","Dagestan Republic","Engels","Gus-Khrustalny","Izhevsk","Kazan","Kemerovo","Kemerovo Oblast","Khabarovsk","Kislovodsk","Komsomolsk-on-Amur","Kostroma","Krasnodar","Krasnodar Krai","Krasnoyarsk","Krasnoyarsk Krai","Kursk","Kursk Oblast","Mezhdurechensk","Mordovia","Moscow","Moscow Oblast","Moskva","Naberezhnye Chelny","Nizhny Novgorod","Nizhny Novgorod Oblast","Novokuznetsk","Novosibirsk","Novosibirsk Oblast","Obninsk","Omsk","Orenburg","Orsk","Oryol Oblast","Perm","Rossiya","Rossosh","Rostov Oblast","Rostov-on-Don","Russia","Russkiy","Saint Petersburg","Samara","Samara Oblast","Saratov","Saratov Oblast","Smolensk","Smolensk Oblast","Sochi","Stavropol","Stavropol Krai","Sverdlovsk Oblast","Tambov Oblast","Tatarstan","Tolyatti","Tomsk","Tyumen","Tyumen Oblast","Udmurt Republic","Ufa","Vladimir","Vladimir Oblast","Vladivostok","Volgograd","Voronezh Oblast","Yamalo-Nenets Autonomous Okrug","Yekaterinburg","Yoshkar-Ola","Zhigulyovsk","Москва","Ульяновск"]},{"countryCode":"RW","cities":["Kigali","Kigali City"]},{"countryCode":"SA","cities":["Al Jubail","Al Khobar","Arar","Dammam","Hail","Jazan","Jeddah","Makkah Province","Riyadh","Yanbu"]},{"countryCode":"SC","cities":[]},{"countryCode":"SD","cities":["Khartoum"]},{"countryCode":"SE","cities":["Gothenburg","Malmö","Örebro","Sollefteå","Stockholm","Sweden","Västerås","Västra Götaland County","Västra Götalands län"]},{"countryCode":"SG","cities":["Singapore"]},{"countryCode":"SI","cities":["Ljubljana","Nova Gorica"]},{"countryCode":"SK","cities":["Bratislava","Dubnica nad Váhom","Piešťany"]},{"countryCode":"SM","cities":[]},{"countryCode":"SN","cities":["Dakar"]},{"countryCode":"SO","cities":["Hargeisa","Mogadishu"]},{"countryCode":"SY","cities":["Damascus"]},{"countryCode":"SZ","cities":[]},{"countryCode":"TG","cities":[]},{"countryCode":"TH","cities":["Bangkok","Hua Hin","Phuket","Samut Prakan","Samut Sakhon","Thailand"]},{"countryCode":"TM","cities":["Ashgabat"]},{"countryCode":"TN","cities":["Sfax","Tunis"]},{"countryCode":"TR","cities":["Adana","Ankara","Artvin","Bodrum","Eskişehir","Istanbul","İstanbul","Izmir","Konya","Manisa","Samsun","Turgutreis","Turkey"]},{"countryCode":"TT","cities":["Port of Spain"]},{"countryCode":"TW","cities":["Kaohsiung City","Taichung City","Taipei","Taipei City"]},{"countryCode":"TZ","cities":["Arusha","Dar es Salaam","Kilimanjaro","Kilimanjaro Region","Mbeya Region","Morogoro Region","Mwanza"]},{"countryCode":"UA","cities":["Aeroflots'kyi","Chernihiv","Chernivtsi","Dnipro","Dnipropetrovsk Oblast","Ivano-Frankivs'ka oblast","Ivano-Frankivsk","Kharkiv","Kharkiv Oblast","Kiev","Kyiv","Kyiv city","Lviv","Melitopol'","Mykolaiv","Odesa","Odessa","Pavlohrad","Poltava","Sums'ka oblast","Ukrainka","Zaporiz'ka oblast","Zhytomyr"]},{"countryCode":"UG","cities":["Kajjansi","Kampala"]},{"countryCode":"US","cities":["Akron","Alaska","Albany","Allentown","Alsip","Altamonte Springs","Ames","Anchorage","Ankeny","Asbury","Ashburn","Ashland","Athens","Atlanta","Auburn","Augusta","Austin","Bangor","Bay City","Belfair","Belgium","Bellingham","Bethlehem","Beverly Hills","Biddeford","Bloomsburg","Boca Raton","Bogota","Boise","Boston","Bothell","Boulder","Bozeman","Branson","Breckenridge","Bridgeview","Brookings","Broomfield","Burlington","Calais","Caldwell","California","California City","Calumet City","Capitol Heights","Cary","Cedar Rapids","Champaign","Chapel Hill","Charleston","Charlotte","Chicago","Chico","Cincinnati","City of Orange","Cleveland","Colorado","Colorado Springs","Columbia","Columbus","Corpus Christi","Covina","Dallas","Dallas Center","Danbury","Dayton","Dearborn","DeKalb","Denver","Des Moines","Detroit","Doral","Douglasville","Eagle","East Troy","Eden","Edmond","El Paso","Elgin","Elk Grove Village","Euclid","Eureka","Evanston","Fairfield","Falls Church","Fayetteville","Florida","Florida City","Folsom","Fort Collins","Fort Lauderdale","Fort Lee","Fort Wayne","Fort Worth","Foster","Framingham","Fraser","Frisco","Garden City","Gardnerville","Georgetown","Georgia","Glendale","Grand Prairie","Grand Rapids","Grants Pass","Gresham","Gurnee","Hallandale Beach","Harrisonburg","Hartford","Harwood Heights","Hawaii","Hebron","Hoboken","Hollywood","Houston","Howland Township","Huntington Beach","Huxley","Idaho Falls","Illinois","Indiana","Indianapolis","Inkster","Iowa City","Irvine","Ithaca","Jersey City","Joliet","Jupiter","Kalamazoo","Kaneohe","Kansas City","Keene","Kittery","Lancaster","Las Vegas","Lawrenceville","Ledyard","Leominster","Lewiston","Liberty Township","Lincoln","Little Rock","Los Angeles","Louisiana","Louisville","Lowell","Lynchburg","Lynn","Lynnwood","Manchester","Manhattan","Mashantucket","Massachusetts","Mentor","Meridian","Miami","Miami Beach","Michigan","Middleton","Middletown","Milltown","Milwaukee","Minneapolis","Montana","Mount Holly","Mountain Home","Mountain View","Nampa","Naples","Nashville","Nevada","New Britain","New Haven","New Jersey","New London","New Orleans","New York","Newark","Niles","Normal","Norwalk","Oak Park","Ohio","Okeechobee","Omaha","Ontario","Oregon","Orlando","Overland Park","Palisades Park","Paradise","Paramus","Passaic","Paterson","Pennsylvania","Peoria","Philadelphia","Phoenix","Pittsburgh","Plantation","Pompton Lakes","Port Townsend","Portland","Providence","Provo","Quincy","Rancho Cucamonga","Reno","Rhode Island","Rochester Hills","Rock Island","Rockford","Roseburg","Sacramento","Saint Charles","Saint Croix Falls","Saint Petersburg","Salem","Salisbury","Salt Lake City","San Antonio","San Diego","San Francisco","San Jose","San Saba","Santa Monica","Schererville","Scranton","Seattle","Shelby charter Township","Shrewsbury","Silver Springs","Sioux City","Sioux Falls","Skokie","Sonoma","South Carolina","South Lake Tahoe","Southington","Sparta Township","Spokane","Springfield","Stamford","Sterling","Tacoma","Tampa","Texas","Toledo","Torrance","Tulsa","United States","United States, United States","Urbana","Utah","Vail","Villa Park","Virginia","Waco","Wakefield","Warren","Washington","Wasilla","Waterloo","Wausau","Weehawken","Wenatchee","West Greenwich","West Jordan","West Lafayette","West Palm Beach","West Warwick","Westminster","Whitehall","Wilkes-Barre","Worcester"]},{"countryCode":"UY","cities":["Melo","Montevideo","Montevideo Department","Paysandú","Punta del Este"]},{"countryCode":"UZ","cities":["Qarshi","Tashkent","Ўзбекистон"]},{"countryCode":"VA","cities":["Vatican City"]},{"countryCode":"VE","cities":["Anzoategui","Aragua","Barcelona","Barinas","Barquisimeto","Cagua","Calabozo","Capital District","Carabobo","Caracas","Carrizal Municipality","Carupano","Coro","Cumana","El Tigre","Falcón","Guacara","Guarenas","Guárico","Guayana City","Lara","Lecheria","Maracaibo","Maracay","Maturin","Merida","Mérida","Miranda","Monagas","Moron","Nueva Esparta","Palo Negro","Pampatar","Pariaguán","Porlamar","Portuguesa","Puerto La Cruz","Punto Fijo","San Antonio de Los Altos","San Cristobal","San Diego","San Felipe","San Fernando de Apure","Táchira","Upata","Valencia","Valera","Valle De La Pascua","Vargas","Venezuela","Venezuela, Venezuela","Yaracuy","Yaritagua","Zulia"]},{"countryCode":"VG","cities":[]},{"countryCode":"VN","cities":["Ho Chi Minh City","Long Xuyên"]},{"countryCode":"VU","cities":[]},{"countryCode":"YE","cities":["Sana'a"]},{"countryCode":"ZA","cities":["Cape Town","Centurion","Durban","Free State","Gauteng","Germiston","Johannesburg","Johannesburg South","Kempton Park","Midrand","Mpumalanga","Polokwane","Pretoria","Randburg","South Africa"]},{"countryCode":"ZM","cities":["Lusaka","Lusaka Province"]},{"countryCode":"ZW","cities":["Bulawayo","Harare"]}]